pynws/__init__.py
pynws/_version.py
pynws/const.py
pynws/forecast.py
pynws/nws.py
pynws/raw_data.py
pynws/simple_nws.py
pynws/units.py
pynws/urls.py
pynws/backports/__init__.py
pynws/backports/enum.py
pynws-2.1.0.dist-info/licenses/LICENSE
pynws-2.1.0.dist-info/METADATA
pynws-2.1.0.dist-info/WHEEL
pynws-2.1.0.dist-info/top_level.txt
pynws-2.1.0.dist-info/RECORD
