Metadata-Version: 2.4
Name: pynws
Version: 2.1.0
Summary: Python library to retrieve observations and forecasts from NWS/NOAA
Author-email: Matthew Flamm <matthewhflamm0@gmail.com>
License-Expression: MIT
Project-URL: Repository, https://github.com/MatthewFlamm/pynws
Project-URL: Bug Tracker, https://github.com/MatthewFlamm/pynws/issues
Keywords: nws,weather
Classifier: Programming Language :: Python :: 3.9
Classifier: Programming Language :: Python :: 3.10
Classifier: Programming Language :: Python :: 3.11
Classifier: Programming Language :: Python :: 3.12
Classifier: Programming Language :: Python :: 3.13
Requires-Python: >=3.9
License-File: LICENSE
Requires-Dist: aiohttp
Requires-Dist: metar
Requires-Dist: yarl
Provides-Extra: retry
Requires-Dist: tenacity; extra == "retry"
Dynamic: license-file
